LICENSE
MANIFEST.in
README.rst
setup.cfg
setup.py
django_sphinx_generator/__init__.py
django_sphinx_generator/generator.py
django_sphinx_generator/settings.py
django_sphinx_generator.egg-info/PKG-INFO
django_sphinx_generator.egg-info/SOURCES.txt
django_sphinx_generator.egg-info/dependency_links.txt
django_sphinx_generator.egg-info/requires.txt
django_sphinx_generator.egg-info/top_level.txt
django_sphinx_generator/management/commands/generate_app_documentation.py
django_sphinx_generator/templates/django_sphinx_generator/index.rst.j2
django_sphinx_generator/templates/django_sphinx_generator/module_index.rst.j2
django_sphinx_generator/templates/django_sphinx_generator/modules.rst.j2